pastoke/__init__.py
pastoke/pastoke.py
pastoke-0.1.1.dist-info/LICENSE.txt
pastoke-0.1.1.dist-info/METADATA
pastoke-0.1.1.dist-info/WHEEL
pastoke-0.1.1.dist-info/top_level.txt
pastoke-0.1.1.dist-info/RECORD
