Metadata-Version: 2.1
Name: pastoke
Version: 0.1.1
Summary: paste jokes script
Home-page: https://github.com/streanger/pastoke
Author: streanger
Author-email: divisionexe@gmail.com
License: MIT
Platform: UNKNOWN
Classifier: Programming Language :: Python :: 3
Classifier: License :: OSI Approved :: MIT License
Classifier: Operating System :: OS Independent
Requires-Dist: pyperclip
